[
  {
    "currency_code": "KHR",
    "unit": 100,
    "rate": {
      "date": "2024-05-30",
      "buying_rate": 0.1143,
      "selling_rate": 0.1157,
      "middle_rate": 0.115
    }
  },
  {
    "currency_code": "SDR",
    "unit": 1,
    "rate": {
      "date": "2024-05-30",
      "buying_rate": null,
      "selling_rate": null,
      "middle_rate": 6.2431
    }
  },
  {
    "currency_code": "VND",
    "unit": 100,
    "rate": {
      "date": "2024-05-30",
      "buying_rate": 0.0185,
      "selling_rate": 0.0185,
      "middle_rate": 0.0185
    }
  },
  {
    "currency_code": "USD",
    "unit": 1,
    "rate": {
      "date": "2024-05-30",
      "buying_rate": 4.715,
      "selling_rate": 4.72,
      "middle_rate": 4.7175
    }
  },
  {
    "currency_code": "TWD",
    "unit": 100,
    "rate": {
      "date": "2024-05-30",
      "buying_rate": 14.5448,
      "selling_rate": 14.5737,
      "middle_rate": 14.5593
    }
  },
  {
    "currency_code": "THB",
    "unit": 100,
    "rate": {
      "date": "2024-05-30",
      "buying_rate": 12.7847,
      "selling_rate": 12.8017,
      "middle_rate": 12.7932
    }
  },
  {
    "currency_code": "SGD",
    "unit": 1,
    "rate": {
      "date": "2024-05-30",
      "buying_rate": 3.4851,
      "selling_rate": 3.4901,
      "middle_rate": 3.4876
    }
  },
  {
    "currency_code": "SAR",
    "unit": 100,
    "rate": {
      "date": "2024-05-30",
      "buying_rate": 125.6998,
      "selling_rate": 125.8499,
      "middle_rate": 125.7749
    }
  },
  {
    "currency_code": "PKR",
    "unit": 100,
    "rate": {
      "date": "2024-05-30",
      "buying_rate": 1.691,
      "selling_rate": 1.6959,
      "middle_rate": 1.6934
    }
  },
  {
    "currency_code": "PHP",
    "unit": 100,
    "rate": {
      "date": "2024-05-30",
      "buying_rate": 8.0461,
      "selling_rate": 8.0574,
      "middle_rate": 8.0517
    }
  },
  {
    "currency_code": "NZD",
    "unit": 1,
    "rate": {
      "date": "2024-05-30",
      "buying_rate": 2.8785,
      "selling_rate": 2.8834,
      "middle_rate": 2.881
    }
  },
  {
    "currency_code": "NPR",
    "unit": 100,
    "rate": {
      "date": "2024-05-30",
      "buying_rate": 3.5353,
      "selling_rate": 3.5396,
      "middle_rate": 3.5374
    }
  },
  {
    "currency_code": "MMK",
    "unit": 100,
    "rate": {
      "date": "2024-05-30",
      "buying_rate": 0.2252,
      "selling_rate": 0.2254,
      "middle_rate": 0.2253
    }
  },
  {
    "currency_code": "KRW",
    "unit": 100,
    "rate": {
      "date": "2024-05-30",
      "buying_rate": 0.3429,
      "selling_rate": 0.3434,
      "middle_rate": 0.3432
    }
  },
  {
    "currency_code": "AED",
    "unit": 100,
    "rate": {
      "date": "2024-05-30",
      "buying_rate": 128.3552,
      "selling_rate": 128.5193,
      "middle_rate": 128.4373
    }
  },
  {
    "currency_code": "JPY",
    "unit": 100,
    "rate": {
      "date": "2024-05-30",
      "buying_rate": 2.9959,
      "selling_rate": 2.9997,
      "middle_rate": 2.9978
    }
  },
  {
    "currency_code": "INR",
    "unit": 100,
    "rate": {
      "date": "2024-05-30",
      "buying_rate": 5.6533,
      "selling_rate": 5.66,
      "middle_rate": 5.6567
    }
  },
  {
    "currency_code": "IDR",
    "unit": 100,
    "rate": {
      "date": "2024-05-30",
      "buying_rate": 0.0292,
      "selling_rate": 0.0292,
      "middle_rate": 0.0292
    }
  },
  {
    "currency_code": "HKD",
    "unit": 100,
    "rate": {
      "date": "2024-05-30",
      "buying_rate": 60.3489,
      "selling_rate": 60.4137,
      "middle_rate": 60.3813
    }
  },
  {
    "currency_code": "GBP",
    "unit": 1,
    "rate": {
      "date": "2024-05-30",
      "buying_rate": 5.9838,
      "selling_rate": 5.993,
      "middle_rate": 5.9884
    }
  },
  {
    "currency_code": "EUR",
    "unit": 1,
    "rate": {
      "date": "2024-05-30",
      "buying_rate": 5.0898,
      "selling_rate": 5.0971,
      "middle_rate": 5.0935
    }
  },
  {
    "currency_code": "EGP",
    "unit": 1,
    "rate": {
      "date": "2024-05-30",
      "buying_rate": 0.0994,
      "selling_rate": 0.0997,
      "middle_rate": 0.0995
    }
  },
  {
    "currency_code": "CNY",
    "unit": 1,
    "rate": {
      "date": "2024-05-30",
      "buying_rate": 0.6504,
      "selling_rate": 0.6511,
      "middle_rate": 0.6508
    }
  },
  {
    "currency_code": "CHF",
    "unit": 1,
    "rate": {
      "date": "2024-05-30",
      "buying_rate": 5.1603,
      "selling_rate": 5.1681,
      "middle_rate": 5.1642
    }
  },
  {
    "currency_code": "CAD",
    "unit": 1,
    "rate": {
      "date": "2024-05-30",
      "buying_rate": 3.4363,
      "selling_rate": 3.4402,
      "middle_rate": 3.4383
    }
  },
  {
    "currency_code": "BND",
    "unit": 1,
    "rate": {
      "date": "2024-05-30",
      "buying_rate": 3.4851,
      "selling_rate": 3.4901,
      "middle_rate": 3.4876
    }
  },
  {
    "currency_code": "AUD",
    "unit": 1,
    "rate": {
      "date": "2024-05-30",
      "buying_rate": 3.1166,
      "selling_rate": 3.1209,
      "middle_rate": 3.1187
    }
  }
]
