[
    {
        "rate": {
            "buying_rate": 3.498,
            "date": "2009-09-14",
            "selling_rate": 3.503,
            "middle_rate": 3.5005
        },
        "currency_code": "USD",
        "unit": 1
    },
    {
        "rate": {
            "buying_rate": 5.8123,
            "date": "2009-09-14",
            "selling_rate": 5.8223,
            "middle_rate": 5.8173
        },
        "currency_code": "GBP",
        "unit": 1
    },
    {
        "rate": {
            "buying_rate": 5.0857,
            "date": "2009-09-14",
            "selling_rate": 5.0934,
            "middle_rate": 5.0896
        },
        "currency_code": "EUR",
        "unit": 1
    },
    {
        "rate": {
            "buying_rate": 3.8601,
            "date": "2009-09-14",
            "selling_rate": 3.866,
            "middle_rate": 3.863
        },
        "currency_code": "JPY",
        "unit": "100"
    },
    {
        "rate": {
            "buying_rate": 3.3641,
            "date": "2009-09-14",
            "selling_rate": 3.3699,
            "middle_rate": 3.367
        },
        "currency_code": "CHF",
        "unit": 1
    },
    {
        "rate": {
            "buying_rate": 2.9964,
            "date": "2009-09-14",
            "selling_rate": 3.0014,
            "middle_rate": 2.9989
        },
        "currency_code": "AUD",
        "unit": 1
    },
    {
        "rate": {
            "buying_rate": 3.2269,
            "date": "2009-09-14",
            "selling_rate": 3.2333,
            "middle_rate": 3.2301
        },
        "currency_code": "CAD",
        "unit": 1
    },
    {
        "rate": {
            "buying_rate": 2.4528,
            "date": "2009-09-14",
            "selling_rate": 2.4588,
            "middle_rate": 2.4558
        },
        "currency_code": "SGD",
        "unit": 1
    },
    {
        "rate": {
            "buying_rate": 45.1297,
            "date": "2009-09-14",
            "selling_rate": 45.2,
            "middle_rate": 45.1648
        },
        "currency_code": "HKD",
        "unit": "100"
    },
    {
        "rate": {
            "buying_rate": 10.3004,
            "date": "2009-09-14",
            "selling_rate": 10.3181,
            "middle_rate": 10.3092
        },
        "currency_code": "THB",
        "unit": "100"
    },
    {
        "rate": {
            "buying_rate": 7.2303,
            "date": "2009-09-14",
            "selling_rate": 7.2782,
            "middle_rate": 7.2542
        },
        "currency_code": "PHP",
        "unit": "100"
    },
    {
        "rate": {
            "buying_rate": 10.7005,
            "date": "2009-09-14",
            "selling_rate": 10.7191,
            "middle_rate": 10.7098
        },
        "currency_code": "TWD",
        "unit": "100"
    },
    {
        "rate": {
            "buying_rate": 0.2852,
            "date": "2009-09-14",
            "selling_rate": 0.2858,
            "middle_rate": 0.2855
        },
        "currency_code": "KRW",
        "unit": "100"
    },
    {
        "rate": {
            "buying_rate": 0.0352,
            "date": "2009-09-14",
            "selling_rate": 0.0354,
            "middle_rate": 0.0353
        },
        "currency_code": "IDR",
        "unit": "100"
    },
    {
        "rate": {
            "buying_rate": 93.2725,
            "date": "2009-09-14",
            "selling_rate": 93.4133,
            "middle_rate": 93.3429
        },
        "currency_code": "SAR",
        "unit": "100"
    },
    {
        "rate": {
            "buying_rate": 0.0,
            "date": "2009-09-14",
            "selling_rate": 0.0,
            "middle_rate": 5.5448
        },
        "currency_code": "SDR",
        "unit": 1
    },
    {
        "rate": {
            "buying_rate": 0.5122,
            "date": "2009-09-14",
            "selling_rate": 0.513,
            "middle_rate": 0.5126
        },
        "currency_code": "CNY",
        "unit": 1
    },
    {
        "rate": {
            "buying_rate": 2.4596,
            "date": "2009-09-14",
            "selling_rate": 2.4645,
            "middle_rate": 2.462
        },
        "currency_code": "BND",
        "unit": 1
    },
    {
        "rate": {
            "buying_rate": 0.0196,
            "date": "2009-09-14",
            "selling_rate": 0.0197,
            "middle_rate": 0.0196
        },
        "currency_code": "VND",
        "unit": "100"
    },
    {
        "rate": {
            "buying_rate": 0.0839,
            "date": "2009-09-14",
            "selling_rate": 0.0849,
            "middle_rate": 0.0844
        },
        "currency_code": "KHR",
        "unit": "100"
    },
    {
        "rate": {
            "buying_rate": 2.4472,
            "date": "2009-09-14",
            "selling_rate": 2.4542,
            "middle_rate": 2.4507
        },
        "currency_code": "NZD",
        "unit": 1
    },
    {
        "rate": {
            "buying_rate": 0.0,
            "date": "2009-09-14",
            "selling_rate": 0.0,
            "middle_rate": 0.0
        },
        "currency_code": "MMK",
        "unit": "100"
    },
    {
        "rate": {
            "buying_rate": 0.0,
            "date": "2009-09-14",
            "selling_rate": 0.0,
            "middle_rate": 0.0
        },
        "currency_code": "INR",
        "unit": "100"
    },
    {
        "rate": {
            "buying_rate": 0.0,
            "date": "2009-09-14",
            "selling_rate": 0.0,
            "middle_rate": 0.0
        },
        "currency_code": "AED",
        "unit": "100"
    },
    {
        "rate": {
            "buying_rate": 0.0,
            "date": "2009-09-14",
            "selling_rate": 0.0,
            "middle_rate": 0.0
        },
        "currency_code": "PKR",
        "unit": "100"
    },
    {
        "rate": {
            "buying_rate": 0.0,
            "date": "2009-09-14",
            "selling_rate": 0.0,
            "middle_rate": 0.0
        },
        "currency_code": "NPR",
        "unit": "100"
    },
    {
        "rate": {
            "buying_rate": 0.0,
            "date": "2009-09-14",
            "selling_rate": 0.0,
            "middle_rate": 0.0
        },
        "currency_code": "EGP",
        "unit": 1
    }
]