[
    {
        "rate": {
            "buying_rate": 3.0415,
            "date": "2013-01-23",
            "selling_rate": 3.0445,
            "middle_rate": 3.043
        },
        "currency_code": "USD",
        "unit": 1
    },
    {
        "rate": {
            "buying_rate": 4.8202,
            "date": "2013-01-23",
            "selling_rate": 4.8252,
            "middle_rate": 4.8227
        },
        "currency_code": "GBP",
        "unit": 1
    },
    {
        "rate": {
            "buying_rate": 4.0443,
            "date": "2013-01-23",
            "selling_rate": 4.0486,
            "middle_rate": 4.0464
        },
        "currency_code": "EUR",
        "unit": 1
    },
    {
        "rate": {
            "buying_rate": 3.4484,
            "date": "2013-01-23",
            "selling_rate": 3.4526,
            "middle_rate": 3.4505
        },
        "currency_code": "JPY",
        "unit": "100"
    },
    {
        "rate": {
            "buying_rate": 3.268,
            "date": "2013-01-23",
            "selling_rate": 3.273,
            "middle_rate": 3.2705
        },
        "currency_code": "CHF",
        "unit": 1
    },
    {
        "rate": {
            "buying_rate": 3.21,
            "date": "2013-01-23",
            "selling_rate": 3.2138,
            "middle_rate": 3.2119
        },
        "currency_code": "AUD",
        "unit": 1
    },
    {
        "rate": {
            "buying_rate": 3.0676,
            "date": "2013-01-23",
            "selling_rate": 3.0712,
            "middle_rate": 3.0694
        },
        "currency_code": "CAD",
        "unit": 1
    },
    {
        "rate": {
            "buying_rate": 2.4784,
            "date": "2013-01-23",
            "selling_rate": 2.4811,
            "middle_rate": 2.4797
        },
        "currency_code": "SGD",
        "unit": 1
    },
    {
        "rate": {
            "buying_rate": 39.2264,
            "date": "2013-01-23",
            "selling_rate": 39.2702,
            "middle_rate": 39.2483
        },
        "currency_code": "HKD",
        "unit": "100"
    },
    {
        "rate": {
            "buying_rate": 10.1927,
            "date": "2013-01-23",
            "selling_rate": 10.2164,
            "middle_rate": 10.2046
        },
        "currency_code": "THB",
        "unit": "100"
    },
    {
        "rate": {
            "buying_rate": 7.4794,
            "date": "2013-01-23",
            "selling_rate": 7.496,
            "middle_rate": 7.4877
        },
        "currency_code": "PHP",
        "unit": "100"
    },
    {
        "rate": {
            "buying_rate": 10.4879,
            "date": "2013-01-23",
            "selling_rate": 10.5019,
            "middle_rate": 10.4949
        },
        "currency_code": "TWD",
        "unit": "100"
    },
    {
        "rate": {
            "buying_rate": 0.2852,
            "date": "2013-01-23",
            "selling_rate": 0.2856,
            "middle_rate": 0.2854
        },
        "currency_code": "KRW",
        "unit": "100"
    },
    {
        "rate": {
            "buying_rate": 0.0316,
            "date": "2013-01-23",
            "selling_rate": 0.0317,
            "middle_rate": 0.0316
        },
        "currency_code": "IDR",
        "unit": "100"
    },
    {
        "rate": {
            "buying_rate": 81.1002,
            "date": "2013-01-23",
            "selling_rate": 81.1845,
            "middle_rate": 81.1423
        },
        "currency_code": "SAR",
        "unit": "100"
    },
    {
        "rate": {
            "buying_rate": 0.0,
            "date": "2013-01-23",
            "selling_rate": 0.0,
            "middle_rate": 4.6771
        },
        "currency_code": "SDR",
        "unit": 1
    },
    {
        "rate": {
            "buying_rate": 0.4891,
            "date": "2013-01-23",
            "selling_rate": 0.4896,
            "middle_rate": 0.4894
        },
        "currency_code": "CNY",
        "unit": 1
    },
    {
        "rate": {
            "buying_rate": 2.478,
            "date": "2013-01-23",
            "selling_rate": 2.4811,
            "middle_rate": 2.4795
        },
        "currency_code": "BND",
        "unit": 1
    },
    {
        "rate": {
            "buying_rate": 0.0146,
            "date": "2013-01-23",
            "selling_rate": 0.0146,
            "middle_rate": 0.0146
        },
        "currency_code": "VND",
        "unit": "100"
    },
    {
        "rate": {
            "buying_rate": 0.0756,
            "date": "2013-01-23",
            "selling_rate": 0.0765,
            "middle_rate": 0.0761
        },
        "currency_code": "KHR",
        "unit": "100"
    },
    {
        "rate": {
            "buying_rate": 2.5634,
            "date": "2013-01-23",
            "selling_rate": 2.5674,
            "middle_rate": 2.5654
        },
        "currency_code": "NZD",
        "unit": 1
    },
    {
        "rate": {
            "buying_rate": 0.3545,
            "date": "2013-01-23",
            "selling_rate": 0.3548,
            "middle_rate": 0.3547
        },
        "currency_code": "MMK",
        "unit": "100"
    },
    {
        "rate": {
            "buying_rate": 5.6539,
            "date": "2013-01-23",
            "selling_rate": 5.6605,
            "middle_rate": 5.6572
        },
        "currency_code": "INR",
        "unit": "100"
    },
    {
        "rate": {
            "buying_rate": 82.8047,
            "date": "2013-01-23",
            "selling_rate": 82.8932,
            "middle_rate": 82.8489
        },
        "currency_code": "AED",
        "unit": "100"
    },
    {
        "rate": {
            "buying_rate": 3.1125,
            "date": "2013-01-23",
            "selling_rate": 3.1171,
            "middle_rate": 3.1148
        },
        "currency_code": "PKR",
        "unit": "100"
    },
    {
        "rate": {
            "buying_rate": 3.5077,
            "date": "2013-01-23",
            "selling_rate": 3.5521,
            "middle_rate": 3.5299
        },
        "currency_code": "NPR",
        "unit": "100"
    },
    {
        "rate": {
            "buying_rate": 0.4584,
            "date": "2013-01-23",
            "selling_rate": 0.4589,
            "middle_rate": 0.4586
        },
        "currency_code": "EGP",
        "unit": 1
    }
]