[
    {
        "rate": {
            "buying_rate": 4.442,
            "date": "2017-02-24",
            "selling_rate": 4.446,
            "middle_rate": 4.444
        },
        "currency_code": "USD",
        "unit": 1
    },
    {
        "rate": {
            "buying_rate": 5.5667,
            "date": "2017-02-24",
            "selling_rate": 5.5744,
            "middle_rate": 5.5706
        },
        "currency_code": "GBP",
        "unit": 1
    },
    {
        "rate": {
            "buying_rate": 4.6974,
            "date": "2017-02-24",
            "selling_rate": 4.703,
            "middle_rate": 4.7002
        },
        "currency_code": "EUR",
        "unit": 1
    },
    {
        "rate": {
            "buying_rate": 3.9432,
            "date": "2017-02-24",
            "selling_rate": 3.9478,
            "middle_rate": 3.9455
        },
        "currency_code": "JPY",
        "unit": "100"
    },
    {
        "rate": {
            "buying_rate": 4.4111,
            "date": "2017-02-24",
            "selling_rate": 4.4177,
            "middle_rate": 4.4144
        },
        "currency_code": "CHF",
        "unit": 1
    },
    {
        "rate": {
            "buying_rate": 3.4234,
            "date": "2017-02-24",
            "selling_rate": 3.4274,
            "middle_rate": 3.4254
        },
        "currency_code": "AUD",
        "unit": 1
    },
    {
        "rate": {
            "buying_rate": 3.3916,
            "date": "2017-02-24",
            "selling_rate": 3.3952,
            "middle_rate": 3.3934
        },
        "currency_code": "CAD",
        "unit": 1
    },
    {
        "rate": {
            "buying_rate": 3.16,
            "date": "2017-02-24",
            "selling_rate": 3.164,
            "middle_rate": 3.162
        },
        "currency_code": "SGD",
        "unit": 1
    },
    {
        "rate": {
            "buying_rate": 57.2378,
            "date": "2017-02-24",
            "selling_rate": 57.2901,
            "middle_rate": 57.264
        },
        "currency_code": "HKD",
        "unit": "100"
    },
    {
        "rate": {
            "buying_rate": 12.7045,
            "date": "2017-02-24",
            "selling_rate": 12.7207,
            "middle_rate": 12.7126
        },
        "currency_code": "THB",
        "unit": "100"
    },
    {
        "rate": {
            "buying_rate": 8.8504,
            "date": "2017-02-24",
            "selling_rate": 8.8603,
            "middle_rate": 8.8553
        },
        "currency_code": "PHP",
        "unit": "100"
    },
    {
        "rate": {
            "buying_rate": 14.4615,
            "date": "2017-02-24",
            "selling_rate": 14.4892,
            "middle_rate": 14.4753
        },
        "currency_code": "TWD",
        "unit": "100"
    },
    {
        "rate": {
            "buying_rate": 0.3922,
            "date": "2017-02-24",
            "selling_rate": 0.3932,
            "middle_rate": 0.3927
        },
        "currency_code": "KRW",
        "unit": "100"
    },
    {
        "rate": {
            "buying_rate": 0.0333,
            "date": "2017-02-24",
            "selling_rate": 0.0334,
            "middle_rate": 0.0333
        },
        "currency_code": "IDR",
        "unit": "100"
    },
    {
        "rate": {
            "buying_rate": 118.4407,
            "date": "2017-02-24",
            "selling_rate": 118.56,
            "middle_rate": 118.5003
        },
        "currency_code": "SAR",
        "unit": "100"
    },
    {
        "rate": {
            "buying_rate": 0.0,
            "date": "2017-02-24",
            "selling_rate": 0.0,
            "middle_rate": 6.0053
        },
        "currency_code": "SDR",
        "unit": 1
    },
    {
        "rate": {
            "buying_rate": 0.6461,
            "date": "2017-02-24",
            "selling_rate": 0.6468,
            "middle_rate": 0.6464
        },
        "currency_code": "CNY",
        "unit": 1
    },
    {
        "rate": {
            "buying_rate": 3.1593,
            "date": "2017-02-24",
            "selling_rate": 3.1644,
            "middle_rate": 3.1619
        },
        "currency_code": "BND",
        "unit": 1
    },
    {
        "rate": {
            "buying_rate": 0.0195,
            "date": "2017-02-24",
            "selling_rate": 0.0195,
            "middle_rate": 0.0195
        },
        "currency_code": "VND",
        "unit": "100"
    },
    {
        "rate": {
            "buying_rate": 0.1104,
            "date": "2017-02-24",
            "selling_rate": 0.1118,
            "middle_rate": 0.1111
        },
        "currency_code": "KHR",
        "unit": "100"
    },
    {
        "rate": {
            "buying_rate": 3.2111,
            "date": "2017-02-24",
            "selling_rate": 3.2149,
            "middle_rate": 3.213
        },
        "currency_code": "NZD",
        "unit": 1
    },
    {
        "rate": {
            "buying_rate": 0.3247,
            "date": "2017-02-24",
            "selling_rate": 0.325,
            "middle_rate": 0.3248
        },
        "currency_code": "MMK",
        "unit": "100"
    },
    {
        "rate": {
            "buying_rate": 6.6602,
            "date": "2017-02-24",
            "selling_rate": 6.6672,
            "middle_rate": 6.6637
        },
        "currency_code": "INR",
        "unit": "100"
    },
    {
        "rate": {
            "buying_rate": 120.9333,
            "date": "2017-02-24",
            "selling_rate": 121.0488,
            "middle_rate": 120.991
        },
        "currency_code": "AED",
        "unit": "100"
    },
    {
        "rate": {
            "buying_rate": 4.2365,
            "date": "2017-02-24",
            "selling_rate": 4.2424,
            "middle_rate": 4.2394
        },
        "currency_code": "PKR",
        "unit": "100"
    },
    {
        "rate": {
            "buying_rate": 4.1375,
            "date": "2017-02-24",
            "selling_rate": 4.1513,
            "middle_rate": 4.1444
        },
        "currency_code": "NPR",
        "unit": "100"
    },
    {
        "rate": {
            "buying_rate": 0.2776,
            "date": "2017-02-24",
            "selling_rate": 0.2796,
            "middle_rate": 0.2786
        },
        "currency_code": "EGP",
        "unit": 1
    }
]