[
    {
        "rate": {
            "buying_rate": 3.281,
            "date": "2014-10-01",
            "selling_rate": 3.283,
            "middle_rate": 3.282
        },
        "currency_code": "USD",
        "unit": 1
    },
    {
        "rate": {
            "buying_rate": 5.3119,
            "date": "2014-10-01",
            "selling_rate": 5.3162,
            "middle_rate": 5.3141
        },
        "currency_code": "GBP",
        "unit": 1
    },
    {
        "rate": {
            "buying_rate": 4.1393,
            "date": "2014-10-01",
            "selling_rate": 4.1425,
            "middle_rate": 4.1409
        },
        "currency_code": "EUR",
        "unit": 1
    },
    {
        "rate": {
            "buying_rate": 2.9852,
            "date": "2014-10-01",
            "selling_rate": 2.9883,
            "middle_rate": 2.9868
        },
        "currency_code": "JPY",
        "unit": "100"
    },
    {
        "rate": {
            "buying_rate": 3.4306,
            "date": "2014-10-01",
            "selling_rate": 3.4345,
            "middle_rate": 3.4325
        },
        "currency_code": "CHF",
        "unit": 1
    },
    {
        "rate": {
            "buying_rate": 2.8473,
            "date": "2014-10-01",
            "selling_rate": 2.8493,
            "middle_rate": 2.8483
        },
        "currency_code": "AUD",
        "unit": 1
    },
    {
        "rate": {
            "buying_rate": 2.9255,
            "date": "2014-10-01",
            "selling_rate": 2.9281,
            "middle_rate": 2.9268
        },
        "currency_code": "CAD",
        "unit": 1
    },
    {
        "rate": {
            "buying_rate": 2.5701,
            "date": "2014-10-01",
            "selling_rate": 2.5719,
            "middle_rate": 2.571
        },
        "currency_code": "SGD",
        "unit": 1
    },
    {
        "rate": {
            "buying_rate": 42.2542,
            "date": "2014-10-01",
            "selling_rate": 42.2816,
            "middle_rate": 42.2679
        },
        "currency_code": "HKD",
        "unit": "100"
    },
    {
        "rate": {
            "buying_rate": 10.1047,
            "date": "2014-10-01",
            "selling_rate": 10.1202,
            "middle_rate": 10.1125
        },
        "currency_code": "THB",
        "unit": "100"
    },
    {
        "rate": {
            "buying_rate": 7.2992,
            "date": "2014-10-01",
            "selling_rate": 7.3085,
            "middle_rate": 7.3039
        },
        "currency_code": "PHP",
        "unit": "100"
    },
    {
        "rate": {
            "buying_rate": 10.7644,
            "date": "2014-10-01",
            "selling_rate": 10.7721,
            "middle_rate": 10.7682
        },
        "currency_code": "TWD",
        "unit": "100"
    },
    {
        "rate": {
            "buying_rate": 0.3085,
            "date": "2014-10-01",
            "selling_rate": 0.3088,
            "middle_rate": 0.3086
        },
        "currency_code": "KRW",
        "unit": "100"
    },
    {
        "rate": {
            "buying_rate": 0.0269,
            "date": "2014-10-01",
            "selling_rate": 0.027,
            "middle_rate": 0.0269
        },
        "currency_code": "IDR",
        "unit": "100"
    },
    {
        "rate": {
            "buying_rate": 87.4514,
            "date": "2014-10-01",
            "selling_rate": 87.5187,
            "middle_rate": 87.485
        },
        "currency_code": "SAR",
        "unit": "100"
    },
    {
        "rate": {
            "buying_rate": 0.0,
            "date": "2014-10-01",
            "selling_rate": 0.0,
            "middle_rate": 4.8658
        },
        "currency_code": "SDR",
        "unit": 1
    },
    {
        "rate": {
            "buying_rate": 0.5345,
            "date": "2014-10-01",
            "selling_rate": 0.5349,
            "middle_rate": 0.5347
        },
        "currency_code": "CNY",
        "unit": 1
    },
    {
        "rate": {
            "buying_rate": 2.5693,
            "date": "2014-10-01",
            "selling_rate": 2.5729,
            "middle_rate": 2.5711
        },
        "currency_code": "BND",
        "unit": 1
    },
    {
        "rate": {
            "buying_rate": 0.0154,
            "date": "2014-10-01",
            "selling_rate": 0.0155,
            "middle_rate": 0.0155
        },
        "currency_code": "VND",
        "unit": "100"
    },
    {
        "rate": {
            "buying_rate": 0.0794,
            "date": "2014-10-01",
            "selling_rate": 0.0803,
            "middle_rate": 0.0799
        },
        "currency_code": "KHR",
        "unit": "100"
    },
    {
        "rate": {
            "buying_rate": 2.5513,
            "date": "2014-10-01",
            "selling_rate": 2.5538,
            "middle_rate": 2.5526
        },
        "currency_code": "NZD",
        "unit": 1
    },
    {
        "rate": {
            "buying_rate": 0.3327,
            "date": "2014-10-01",
            "selling_rate": 0.333,
            "middle_rate": 0.3329
        },
        "currency_code": "MMK",
        "unit": "100"
    },
    {
        "rate": {
            "buying_rate": 5.3101,
            "date": "2014-10-01",
            "selling_rate": 5.3138,
            "middle_rate": 5.312
        },
        "currency_code": "INR",
        "unit": "100"
    },
    {
        "rate": {
            "buying_rate": 89.3275,
            "date": "2014-10-01",
            "selling_rate": 89.3917,
            "middle_rate": 89.3596
        },
        "currency_code": "AED",
        "unit": "100"
    },
    {
        "rate": {
            "buying_rate": 3.1947,
            "date": "2014-10-01",
            "selling_rate": 3.2029,
            "middle_rate": 3.1988
        },
        "currency_code": "PKR",
        "unit": "100"
    },
    {
        "rate": {
            "buying_rate": 3.3021,
            "date": "2014-10-01",
            "selling_rate": 3.3377,
            "middle_rate": 3.3199
        },
        "currency_code": "NPR",
        "unit": "100"
    },
    {
        "rate": {
            "buying_rate": 0.4589,
            "date": "2014-10-01",
            "selling_rate": 0.4592,
            "middle_rate": 0.459
        },
        "currency_code": "EGP",
        "unit": 1
    }
]