[
    {
        "rate": {
            "buying_rate": 3.167,
            "date": "2014-07-10",
            "selling_rate": 3.17,
            "middle_rate": 3.1685
        },
        "currency_code": "USD",
        "unit": 1
    },
    {
        "rate": {
            "buying_rate": 5.4339,
            "date": "2014-07-10",
            "selling_rate": 5.4407,
            "middle_rate": 5.4373
        },
        "currency_code": "GBP",
        "unit": 1
    },
    {
        "rate": {
            "buying_rate": 4.3211,
            "date": "2014-07-10",
            "selling_rate": 4.3264,
            "middle_rate": 4.3237
        },
        "currency_code": "EUR",
        "unit": 1
    },
    {
        "rate": {
            "buying_rate": 3.1187,
            "date": "2014-07-10",
            "selling_rate": 3.1219,
            "middle_rate": 3.1203
        },
        "currency_code": "JPY",
        "unit": "100"
    },
    {
        "rate": {
            "buying_rate": 3.5556,
            "date": "2014-07-10",
            "selling_rate": 3.5598,
            "middle_rate": 3.5577
        },
        "currency_code": "CHF",
        "unit": 1
    },
    {
        "rate": {
            "buying_rate": 2.9833,
            "date": "2014-07-10",
            "selling_rate": 2.9877,
            "middle_rate": 2.9855
        },
        "currency_code": "AUD",
        "unit": 1
    },
    {
        "rate": {
            "buying_rate": 2.9729,
            "date": "2014-07-10",
            "selling_rate": 2.9768,
            "middle_rate": 2.9748
        },
        "currency_code": "CAD",
        "unit": 1
    },
    {
        "rate": {
            "buying_rate": 2.5522,
            "date": "2014-07-10",
            "selling_rate": 2.5567,
            "middle_rate": 2.5544
        },
        "currency_code": "SGD",
        "unit": 1
    },
    {
        "rate": {
            "buying_rate": 40.8624,
            "date": "2014-07-10",
            "selling_rate": 40.9038,
            "middle_rate": 40.8831
        },
        "currency_code": "HKD",
        "unit": "100"
    },
    {
        "rate": {
            "buying_rate": 9.8385,
            "date": "2014-07-10",
            "selling_rate": 9.86,
            "middle_rate": 9.8492
        },
        "currency_code": "THB",
        "unit": "100"
    },
    {
        "rate": {
            "buying_rate": 7.3057,
            "date": "2014-07-10",
            "selling_rate": 7.321,
            "middle_rate": 7.3133
        },
        "currency_code": "PHP",
        "unit": "100"
    },
    {
        "rate": {
            "buying_rate": 10.5602,
            "date": "2014-07-10",
            "selling_rate": 10.5843,
            "middle_rate": 10.5722
        },
        "currency_code": "TWD",
        "unit": "100"
    },
    {
        "rate": {
            "buying_rate": 0.3129,
            "date": "2014-07-10",
            "selling_rate": 0.3134,
            "middle_rate": 0.3132
        },
        "currency_code": "KRW",
        "unit": "100"
    },
    {
        "rate": {
            "buying_rate": 0.0273,
            "date": "2014-07-10",
            "selling_rate": 0.0274,
            "middle_rate": 0.0274
        },
        "currency_code": "IDR",
        "unit": "100"
    },
    {
        "rate": {
            "buying_rate": 84.4443,
            "date": "2014-07-10",
            "selling_rate": 84.5288,
            "middle_rate": 84.4866
        },
        "currency_code": "SAR",
        "unit": "100"
    },
    {
        "rate": {
            "buying_rate": 0.0,
            "date": "2014-07-10",
            "selling_rate": 0.0,
            "middle_rate": 4.8946
        },
        "currency_code": "SDR",
        "unit": 1
    },
    {
        "rate": {
            "buying_rate": 0.5108,
            "date": "2014-07-10",
            "selling_rate": 0.5113,
            "middle_rate": 0.5111
        },
        "currency_code": "CNY",
        "unit": 1
    },
    {
        "rate": {
            "buying_rate": 2.5516,
            "date": "2014-07-10",
            "selling_rate": 2.556,
            "middle_rate": 2.5538
        },
        "currency_code": "BND",
        "unit": 1
    },
    {
        "rate": {
            "buying_rate": 0.0149,
            "date": "2014-07-10",
            "selling_rate": 0.0149,
            "middle_rate": 0.0149
        },
        "currency_code": "VND",
        "unit": "100"
    },
    {
        "rate": {
            "buying_rate": 0.0779,
            "date": "2014-07-10",
            "selling_rate": 0.0789,
            "middle_rate": 0.0784
        },
        "currency_code": "KHR",
        "unit": "100"
    },
    {
        "rate": {
            "buying_rate": 2.7939,
            "date": "2014-07-10",
            "selling_rate": 2.7975,
            "middle_rate": 2.7957
        },
        "currency_code": "NZD",
        "unit": 1
    },
    {
        "rate": {
            "buying_rate": 0.3265,
            "date": "2014-07-10",
            "selling_rate": 0.3268,
            "middle_rate": 0.3266
        },
        "currency_code": "MMK",
        "unit": "100"
    },
    {
        "rate": {
            "buying_rate": 5.3084,
            "date": "2014-07-10",
            "selling_rate": 5.3152,
            "middle_rate": 5.3118
        },
        "currency_code": "INR",
        "unit": "100"
    },
    {
        "rate": {
            "buying_rate": 86.2238,
            "date": "2014-07-10",
            "selling_rate": 86.3078,
            "middle_rate": 86.2658
        },
        "currency_code": "AED",
        "unit": "100"
    },
    {
        "rate": {
            "buying_rate": 3.2022,
            "date": "2014-07-10",
            "selling_rate": 3.2118,
            "middle_rate": 3.207
        },
        "currency_code": "PKR",
        "unit": "100"
    },
    {
        "rate": {
            "buying_rate": 3.2952,
            "date": "2014-07-10",
            "selling_rate": 3.333,
            "middle_rate": 3.3141
        },
        "currency_code": "NPR",
        "unit": "100"
    },
    {
        "rate": {
            "buying_rate": 0.4429,
            "date": "2014-07-10",
            "selling_rate": 0.4434,
            "middle_rate": 0.4431
        },
        "currency_code": "EGP",
        "unit": 1
    }
]