[
    {
        "rate": {
            "buying_rate": 3.19,
            "date": "2012-06-22",
            "selling_rate": 3.193,
            "middle_rate": 3.1915
        },
        "currency_code": "USD",
        "unit": 1
    },
    {
        "rate": {
            "buying_rate": 4.9831,
            "date": "2012-06-22",
            "selling_rate": 4.9881,
            "middle_rate": 4.9856
        },
        "currency_code": "GBP",
        "unit": 1
    },
    {
        "rate": {
            "buying_rate": 4.0031,
            "date": "2012-06-22",
            "selling_rate": 4.0079,
            "middle_rate": 4.0055
        },
        "currency_code": "EUR",
        "unit": 1
    },
    {
        "rate": {
            "buying_rate": 3.9686,
            "date": "2012-06-22",
            "selling_rate": 3.9744,
            "middle_rate": 3.9715
        },
        "currency_code": "JPY",
        "unit": "100"
    },
    {
        "rate": {
            "buying_rate": 3.333,
            "date": "2012-06-22",
            "selling_rate": 3.3372,
            "middle_rate": 3.3351
        },
        "currency_code": "CHF",
        "unit": 1
    },
    {
        "rate": {
            "buying_rate": 3.197,
            "date": "2012-06-22",
            "selling_rate": 3.201,
            "middle_rate": 3.199
        },
        "currency_code": "AUD",
        "unit": 1
    },
    {
        "rate": {
            "buying_rate": 3.1028,
            "date": "2012-06-22",
            "selling_rate": 3.1066,
            "middle_rate": 3.1047
        },
        "currency_code": "CAD",
        "unit": 1
    },
    {
        "rate": {
            "buying_rate": 2.4967,
            "date": "2012-06-22",
            "selling_rate": 2.501,
            "middle_rate": 2.4988
        },
        "currency_code": "SGD",
        "unit": 1
    },
    {
        "rate": {
            "buying_rate": 41.1067,
            "date": "2012-06-22",
            "selling_rate": 41.1501,
            "middle_rate": 41.1284
        },
        "currency_code": "HKD",
        "unit": "100"
    },
    {
        "rate": {
            "buying_rate": 10.0314,
            "date": "2012-06-22",
            "selling_rate": 10.0472,
            "middle_rate": 10.0393
        },
        "currency_code": "THB",
        "unit": "100"
    },
    {
        "rate": {
            "buying_rate": 7.52,
            "date": "2012-06-22",
            "selling_rate": 7.5307,
            "middle_rate": 7.5253
        },
        "currency_code": "PHP",
        "unit": "100"
    },
    {
        "rate": {
            "buying_rate": 10.6475,
            "date": "2012-06-22",
            "selling_rate": 10.6611,
            "middle_rate": 10.6543
        },
        "currency_code": "TWD",
        "unit": "100"
    },
    {
        "rate": {
            "buying_rate": 0.275,
            "date": "2012-06-22",
            "selling_rate": 0.2755,
            "middle_rate": 0.2753
        },
        "currency_code": "KRW",
        "unit": "100"
    },
    {
        "rate": {
            "buying_rate": 0.0338,
            "date": "2012-06-22",
            "selling_rate": 0.0339,
            "middle_rate": 0.0338
        },
        "currency_code": "IDR",
        "unit": "100"
    },
    {
        "rate": {
            "buying_rate": 85.0576,
            "date": "2012-06-22",
            "selling_rate": 85.1421,
            "middle_rate": 85.0999
        },
        "currency_code": "SAR",
        "unit": "100"
    },
    {
        "rate": {
            "buying_rate": 0.0,
            "date": "2012-06-22",
            "selling_rate": 0.0,
            "middle_rate": 4.8543
        },
        "currency_code": "SDR",
        "unit": 1
    },
    {
        "rate": {
            "buying_rate": 0.5011,
            "date": "2012-06-22",
            "selling_rate": 0.5017,
            "middle_rate": 0.5014
        },
        "currency_code": "CNY",
        "unit": 1
    },
    {
        "rate": {
            "buying_rate": 2.4977,
            "date": "2012-06-22",
            "selling_rate": 2.5006,
            "middle_rate": 2.4991
        },
        "currency_code": "BND",
        "unit": 1
    },
    {
        "rate": {
            "buying_rate": 0.0152,
            "date": "2012-06-22",
            "selling_rate": 0.0153,
            "middle_rate": 0.0153
        },
        "currency_code": "VND",
        "unit": "100"
    },
    {
        "rate": {
            "buying_rate": 0.077,
            "date": "2012-06-22",
            "selling_rate": 0.078,
            "middle_rate": 0.0775
        },
        "currency_code": "KHR",
        "unit": "100"
    },
    {
        "rate": {
            "buying_rate": 2.5093,
            "date": "2012-06-22",
            "selling_rate": 2.5132,
            "middle_rate": 2.5112
        },
        "currency_code": "NZD",
        "unit": 1
    },
    {
        "rate": {
            "buying_rate": 0.3731,
            "date": "2012-06-22",
            "selling_rate": 0.3735,
            "middle_rate": 0.3733
        },
        "currency_code": "MMK",
        "unit": "100"
    },
    {
        "rate": {
            "buying_rate": 5.5779,
            "date": "2012-06-22",
            "selling_rate": 5.5841,
            "middle_rate": 5.581
        },
        "currency_code": "INR",
        "unit": "100"
    },
    {
        "rate": {
            "buying_rate": 86.85,
            "date": "2012-06-22",
            "selling_rate": 86.9364,
            "middle_rate": 86.8932
        },
        "currency_code": "AED",
        "unit": "100"
    },
    {
        "rate": {
            "buying_rate": 3.3807,
            "date": "2012-06-22",
            "selling_rate": 3.3856,
            "middle_rate": 3.3832
        },
        "currency_code": "PKR",
        "unit": "100"
    },
    {
        "rate": {
            "buying_rate": 3.6828,
            "date": "2012-06-22",
            "selling_rate": 3.7293,
            "middle_rate": 3.706
        },
        "currency_code": "NPR",
        "unit": "100"
    },
    {
        "rate": {
            "buying_rate": 0.5268,
            "date": "2012-06-22",
            "selling_rate": 0.5279,
            "middle_rate": 0.5273
        },
        "currency_code": "EGP",
        "unit": 1
    }
]