[
    {
        "rate": {
            "buying_rate": 3.6738,
            "date": "2006-09-22",
            "selling_rate": 3.6778,
            "middle_rate": 3.676
        },
        "currency_code": "USD",
        "unit": 1
    },
    {
        "rate": {
            "buying_rate": 6.9881,
            "date": "2006-09-22",
            "selling_rate": 6.9979,
            "middle_rate": 6.9949
        },
        "currency_code": "GBP",
        "unit": 1
    },
    {
        "rate": {
            "buying_rate": 4.697,
            "date": "2006-09-22",
            "selling_rate": 4.7015,
            "middle_rate": 4.6996
        },
        "currency_code": "EUR",
        "unit": 1
    },
    {
        "rate": {
            "buying_rate": 3.1555,
            "date": "2006-09-22",
            "selling_rate": 3.1598,
            "middle_rate": 3.1577
        },
        "currency_code": "JPY",
        "unit": "100"
    },
    {
        "rate": {
            "buying_rate": 2.9568,
            "date": "2006-09-22",
            "selling_rate": 2.9612,
            "middle_rate": 2.9591
        },
        "currency_code": "CHF",
        "unit": 1
    },
    {
        "rate": {
            "buying_rate": 0.0,
            "date": "2006-09-22",
            "selling_rate": 0.0,
            "middle_rate": 2.7792
        },
        "currency_code": "AUD",
        "unit": 1
    },
    {
        "rate": {
            "buying_rate": 0.0,
            "date": "2006-09-22",
            "selling_rate": 0.0,
            "middle_rate": 3.2842
        },
        "currency_code": "CAD",
        "unit": 1
    },
    {
        "rate": {
            "buying_rate": 2.3186,
            "date": "2006-09-22",
            "selling_rate": 2.3223,
            "middle_rate": 2.3204
        },
        "currency_code": "SGD",
        "unit": 1
    },
    {
        "rate": {
            "buying_rate": 47.2077,
            "date": "2006-09-22",
            "selling_rate": 47.2612,
            "middle_rate": 47.2348
        },
        "currency_code": "HKD",
        "unit": "100"
    },
    {
        "rate": {
            "buying_rate": 9.8078,
            "date": "2006-09-22",
            "selling_rate": 9.8264,
            "middle_rate": 9.8171
        },
        "currency_code": "THB",
        "unit": "100"
    },
    {
        "rate": {
            "buying_rate": 7.3013,
            "date": "2006-09-22",
            "selling_rate": 7.3121,
            "middle_rate": 7.3067
        },
        "currency_code": "PHP",
        "unit": "100"
    },
    {
        "rate": {
            "buying_rate": 0.0,
            "date": "2006-09-22",
            "selling_rate": 0.0,
            "middle_rate": 11.1644
        },
        "currency_code": "TWD",
        "unit": "100"
    },
    {
        "rate": {
            "buying_rate": 0.0,
            "date": "2006-09-22",
            "selling_rate": 0.0,
            "middle_rate": 0.3888
        },
        "currency_code": "KRW",
        "unit": "100"
    },
    {
        "rate": {
            "buying_rate": 0.04,
            "date": "2006-09-22",
            "selling_rate": 0.0401,
            "middle_rate": 0.0401
        },
        "currency_code": "IDR",
        "unit": "100"
    },
    {
        "rate": {
            "buying_rate": 97.9528,
            "date": "2006-09-22",
            "selling_rate": 98.0681,
            "middle_rate": 0.0
        },
        "currency_code": "SAR",
        "unit": "100"
    },
    {
        "rate": {
            "buying_rate": 0.0,
            "date": "2006-09-22",
            "selling_rate": 0.0,
            "middle_rate": 5.446
        },
        "currency_code": "SDR",
        "unit": 1
    },
    {
        "rate": {
            "buying_rate": 0.4641,
            "date": "2006-09-22",
            "selling_rate": 0.4646,
            "middle_rate": 0.4643
        },
        "currency_code": "CNY",
        "unit": 1
    },
    {
        "rate": {
            "buying_rate": 2.3229,
            "date": "2006-09-22",
            "selling_rate": 2.3261,
            "middle_rate": 2.3245
        },
        "currency_code": "BND",
        "unit": 1
    },
    {
        "rate": {
            "buying_rate": 0.0229,
            "date": "2006-09-22",
            "selling_rate": 0.0229,
            "middle_rate": 0.0229
        },
        "currency_code": "VND",
        "unit": "100"
    },
    {
        "rate": {
            "buying_rate": 0.0882,
            "date": "2006-09-22",
            "selling_rate": 0.0892,
            "middle_rate": 0.0887
        },
        "currency_code": "KHR",
        "unit": "100"
    },
    {
        "rate": {
            "buying_rate": 0.0,
            "date": "2006-09-22",
            "selling_rate": 0.0,
            "middle_rate": 0.0
        },
        "currency_code": "NZD",
        "unit": 1
    },
    {
        "rate": {
            "buying_rate": 0.0,
            "date": "2006-09-22",
            "selling_rate": 0.0,
            "middle_rate": 0.0
        },
        "currency_code": "MMK",
        "unit": "100"
    },
    {
        "rate": {
            "buying_rate": 0.0,
            "date": "2006-09-22",
            "selling_rate": 0.0,
            "middle_rate": 0.0
        },
        "currency_code": "INR",
        "unit": "100"
    },
    {
        "rate": {
            "buying_rate": 0.0,
            "date": "2006-09-22",
            "selling_rate": 0.0,
            "middle_rate": 0.0
        },
        "currency_code": "AED",
        "unit": "100"
    },
    {
        "rate": {
            "buying_rate": 0.0,
            "date": "2006-09-22",
            "selling_rate": 0.0,
            "middle_rate": 0.0
        },
        "currency_code": "PKR",
        "unit": "100"
    },
    {
        "rate": {
            "buying_rate": 0.0,
            "date": "2006-09-22",
            "selling_rate": 0.0,
            "middle_rate": 0.0
        },
        "currency_code": "NPR",
        "unit": "100"
    },
    {
        "rate": {
            "buying_rate": 0.0,
            "date": "2006-09-22",
            "selling_rate": 0.0,
            "middle_rate": 0.0
        },
        "currency_code": "EGP",
        "unit": 1
    }
]