[
    {
        "rate": {
            "buying_rate": 3.258,
            "date": "2013-09-17",
            "selling_rate": 3.262,
            "middle_rate": 3.26
        },
        "currency_code": "USD",
        "unit": 1
    },
    {
        "rate": {
            "buying_rate": 5.1786,
            "date": "2013-09-17",
            "selling_rate": 5.1863,
            "middle_rate": 5.1824
        },
        "currency_code": "GBP",
        "unit": 1
    },
    {
        "rate": {
            "buying_rate": 4.3439,
            "date": "2013-09-17",
            "selling_rate": 4.3499,
            "middle_rate": 4.3469
        },
        "currency_code": "EUR",
        "unit": 1
    },
    {
        "rate": {
            "buying_rate": 3.2823,
            "date": "2013-09-17",
            "selling_rate": 3.2866,
            "middle_rate": 3.2845
        },
        "currency_code": "JPY",
        "unit": "100"
    },
    {
        "rate": {
            "buying_rate": 3.5123,
            "date": "2013-09-17",
            "selling_rate": 3.5181,
            "middle_rate": 3.5152
        },
        "currency_code": "CHF",
        "unit": 1
    },
    {
        "rate": {
            "buying_rate": 3.0312,
            "date": "2013-09-17",
            "selling_rate": 3.0359,
            "middle_rate": 3.0336
        },
        "currency_code": "AUD",
        "unit": 1
    },
    {
        "rate": {
            "buying_rate": 3.1539,
            "date": "2013-09-17",
            "selling_rate": 3.1596,
            "middle_rate": 3.1568
        },
        "currency_code": "CAD",
        "unit": 1
    },
    {
        "rate": {
            "buying_rate": 2.5771,
            "date": "2013-09-17",
            "selling_rate": 2.5819,
            "middle_rate": 2.5795
        },
        "currency_code": "SGD",
        "unit": 1
    },
    {
        "rate": {
            "buying_rate": 42.0116,
            "date": "2013-09-17",
            "selling_rate": 42.0686,
            "middle_rate": 42.0401
        },
        "currency_code": "HKD",
        "unit": "100"
    },
    {
        "rate": {
            "buying_rate": 10.2388,
            "date": "2013-09-17",
            "selling_rate": 10.2579,
            "middle_rate": 10.2484
        },
        "currency_code": "THB",
        "unit": "100"
    },
    {
        "rate": {
            "buying_rate": 7.4452,
            "date": "2013-09-17",
            "selling_rate": 7.4577,
            "middle_rate": 7.4514
        },
        "currency_code": "PHP",
        "unit": "100"
    },
    {
        "rate": {
            "buying_rate": 10.9664,
            "date": "2013-09-17",
            "selling_rate": 11.0169,
            "middle_rate": 10.9916
        },
        "currency_code": "TWD",
        "unit": "100"
    },
    {
        "rate": {
            "buying_rate": 0.3001,
            "date": "2013-09-17",
            "selling_rate": 0.3006,
            "middle_rate": 0.3003
        },
        "currency_code": "KRW",
        "unit": "100"
    },
    {
        "rate": {
            "buying_rate": 0.0284,
            "date": "2013-09-17",
            "selling_rate": 0.0285,
            "middle_rate": 0.0285
        },
        "currency_code": "IDR",
        "unit": "100"
    },
    {
        "rate": {
            "buying_rate": 86.8684,
            "date": "2013-09-17",
            "selling_rate": 86.9797,
            "middle_rate": 86.9241
        },
        "currency_code": "SAR",
        "unit": "100"
    },
    {
        "rate": {
            "buying_rate": 0.0,
            "date": "2013-09-17",
            "selling_rate": 0.0,
            "middle_rate": 4.9668
        },
        "currency_code": "SDR",
        "unit": 1
    },
    {
        "rate": {
            "buying_rate": 0.5322,
            "date": "2013-09-17",
            "selling_rate": 0.5329,
            "middle_rate": 0.5326
        },
        "currency_code": "CNY",
        "unit": 1
    },
    {
        "rate": {
            "buying_rate": 2.5771,
            "date": "2013-09-17",
            "selling_rate": 2.5809,
            "middle_rate": 2.579
        },
        "currency_code": "BND",
        "unit": 1
    },
    {
        "rate": {
            "buying_rate": 0.0154,
            "date": "2013-09-17",
            "selling_rate": 0.0155,
            "middle_rate": 0.0154
        },
        "currency_code": "VND",
        "unit": "100"
    },
    {
        "rate": {
            "buying_rate": 0.079,
            "date": "2013-09-17",
            "selling_rate": 0.08,
            "middle_rate": 0.0795
        },
        "currency_code": "KHR",
        "unit": "100"
    },
    {
        "rate": {
            "buying_rate": 2.6618,
            "date": "2013-09-17",
            "selling_rate": 2.666,
            "middle_rate": 2.6639
        },
        "currency_code": "NZD",
        "unit": 1
    },
    {
        "rate": {
            "buying_rate": 0.3362,
            "date": "2013-09-17",
            "selling_rate": 0.3366,
            "middle_rate": 0.3364
        },
        "currency_code": "MMK",
        "unit": "100"
    },
    {
        "rate": {
            "buying_rate": 5.1327,
            "date": "2013-09-17",
            "selling_rate": 5.1407,
            "middle_rate": 5.1367
        },
        "currency_code": "INR",
        "unit": "100"
    },
    {
        "rate": {
            "buying_rate": 88.6965,
            "date": "2013-09-17",
            "selling_rate": 88.8151,
            "middle_rate": 88.7558
        },
        "currency_code": "AED",
        "unit": "100"
    },
    {
        "rate": {
            "buying_rate": 3.0999,
            "date": "2013-09-17",
            "selling_rate": 3.1096,
            "middle_rate": 3.1048
        },
        "currency_code": "PKR",
        "unit": "100"
    },
    {
        "rate": {
            "buying_rate": 3.1922,
            "date": "2013-09-17",
            "selling_rate": 3.2278,
            "middle_rate": 3.21
        },
        "currency_code": "NPR",
        "unit": "100"
    },
    {
        "rate": {
            "buying_rate": 0.4726,
            "date": "2013-09-17",
            "selling_rate": 0.4732,
            "middle_rate": 0.4729
        },
        "currency_code": "EGP",
        "unit": 1
    }
]