[
    {
        "rate": {
            "buying_rate": 3.437,
            "date": "2009-12-17",
            "selling_rate": 3.44,
            "middle_rate": 3.4385
        },
        "currency_code": "USD",
        "unit": 1
    },
    {
        "rate": {
            "buying_rate": 5.5769,
            "date": "2009-12-17",
            "selling_rate": 5.5824,
            "middle_rate": 5.5797
        },
        "currency_code": "GBP",
        "unit": 1
    },
    {
        "rate": {
            "buying_rate": 4.9476,
            "date": "2009-12-17",
            "selling_rate": 4.9522,
            "middle_rate": 4.9499
        },
        "currency_code": "EUR",
        "unit": 1
    },
    {
        "rate": {
            "buying_rate": 3.8257,
            "date": "2009-12-17",
            "selling_rate": 3.8295,
            "middle_rate": 3.8276
        },
        "currency_code": "JPY",
        "unit": "100"
    },
    {
        "rate": {
            "buying_rate": 3.2859,
            "date": "2009-12-17",
            "selling_rate": 3.2903,
            "middle_rate": 3.2881
        },
        "currency_code": "CHF",
        "unit": 1
    },
    {
        "rate": {
            "buying_rate": 3.0627,
            "date": "2009-12-17",
            "selling_rate": 3.0671,
            "middle_rate": 3.0649
        },
        "currency_code": "AUD",
        "unit": 1
    },
    {
        "rate": {
            "buying_rate": 3.2194,
            "date": "2009-12-17",
            "selling_rate": 3.2237,
            "middle_rate": 3.2215
        },
        "currency_code": "CAD",
        "unit": 1
    },
    {
        "rate": {
            "buying_rate": 2.4508,
            "date": "2009-12-17",
            "selling_rate": 2.4564,
            "middle_rate": 2.4536
        },
        "currency_code": "SGD",
        "unit": 1
    },
    {
        "rate": {
            "buying_rate": 44.3118,
            "date": "2009-12-17",
            "selling_rate": 44.3562,
            "middle_rate": 44.334
        },
        "currency_code": "HKD",
        "unit": "100"
    },
    {
        "rate": {
            "buying_rate": 10.3337,
            "date": "2009-12-17",
            "selling_rate": 10.3583,
            "middle_rate": 10.346
        },
        "currency_code": "THB",
        "unit": "100"
    },
    {
        "rate": {
            "buying_rate": 7.3994,
            "date": "2009-12-17",
            "selling_rate": 7.409,
            "middle_rate": 7.4042
        },
        "currency_code": "PHP",
        "unit": "100"
    },
    {
        "rate": {
            "buying_rate": 10.6251,
            "date": "2009-12-17",
            "selling_rate": 10.6383,
            "middle_rate": 10.6317
        },
        "currency_code": "TWD",
        "unit": "100"
    },
    {
        "rate": {
            "buying_rate": 0.2916,
            "date": "2009-12-17",
            "selling_rate": 0.2923,
            "middle_rate": 0.2919
        },
        "currency_code": "KRW",
        "unit": "100"
    },
    {
        "rate": {
            "buying_rate": 0.0363,
            "date": "2009-12-17",
            "selling_rate": 0.0363,
            "middle_rate": 0.0363
        },
        "currency_code": "IDR",
        "unit": "100"
    },
    {
        "rate": {
            "buying_rate": 91.6313,
            "date": "2009-12-17",
            "selling_rate": 91.7187,
            "middle_rate": 91.675
        },
        "currency_code": "SAR",
        "unit": "100"
    },
    {
        "rate": {
            "buying_rate": 0.0,
            "date": "2009-12-17",
            "selling_rate": 0.0,
            "middle_rate": 5.4414
        },
        "currency_code": "SDR",
        "unit": 1
    },
    {
        "rate": {
            "buying_rate": 0.5033,
            "date": "2009-12-17",
            "selling_rate": 0.5038,
            "middle_rate": 0.5035
        },
        "currency_code": "CNY",
        "unit": 1
    },
    {
        "rate": {
            "buying_rate": 2.4508,
            "date": "2009-12-17",
            "selling_rate": 2.4564,
            "middle_rate": 2.4536
        },
        "currency_code": "BND",
        "unit": 1
    },
    {
        "rate": {
            "buying_rate": 0.0186,
            "date": "2009-12-17",
            "selling_rate": 0.0186,
            "middle_rate": 0.0186
        },
        "currency_code": "VND",
        "unit": "100"
    },
    {
        "rate": {
            "buying_rate": 0.0817,
            "date": "2009-12-17",
            "selling_rate": 0.0827,
            "middle_rate": 0.0822
        },
        "currency_code": "KHR",
        "unit": "100"
    },
    {
        "rate": {
            "buying_rate": 2.4489,
            "date": "2009-12-17",
            "selling_rate": 2.4531,
            "middle_rate": 2.451
        },
        "currency_code": "NZD",
        "unit": 1
    },
    {
        "rate": {
            "buying_rate": 0.0,
            "date": "2009-12-17",
            "selling_rate": 0.0,
            "middle_rate": 0.0
        },
        "currency_code": "MMK",
        "unit": "100"
    },
    {
        "rate": {
            "buying_rate": 0.0,
            "date": "2009-12-17",
            "selling_rate": 0.0,
            "middle_rate": 0.0
        },
        "currency_code": "INR",
        "unit": "100"
    },
    {
        "rate": {
            "buying_rate": 0.0,
            "date": "2009-12-17",
            "selling_rate": 0.0,
            "middle_rate": 0.0
        },
        "currency_code": "AED",
        "unit": "100"
    },
    {
        "rate": {
            "buying_rate": 0.0,
            "date": "2009-12-17",
            "selling_rate": 0.0,
            "middle_rate": 0.0
        },
        "currency_code": "PKR",
        "unit": "100"
    },
    {
        "rate": {
            "buying_rate": 0.0,
            "date": "2009-12-17",
            "selling_rate": 0.0,
            "middle_rate": 0.0
        },
        "currency_code": "NPR",
        "unit": "100"
    },
    {
        "rate": {
            "buying_rate": 0.0,
            "date": "2009-12-17",
            "selling_rate": 0.0,
            "middle_rate": 0.0
        },
        "currency_code": "EGP",
        "unit": 1
    }
]